reference_counter/__init__.py
reference_counter/__version__.py
reference_counter/_compat.py
reference_counter/exceptions.py
reference_counter/reference_counter.py
reference_counter-1.0.2.dist-info/METADATA
reference_counter-1.0.2.dist-info/WHEEL
reference_counter-1.0.2.dist-info/entry_points.txt
reference_counter-1.0.2.dist-info/RECORD
